{"name": "創新", "id": 1276549, "predecessors": [{"name": "文化", "id": 42322}], "successors": [{"name": "抽象", "id": 42487}, {"name": "文字發明者", "id": 259252}, {"name": "語言創造者", "id": 1231314}, {"name": "虚构发明家", "id": 1372393}, {"name": "19世纪发明", "id": 8644665}, {"name": "公司创始人", "id": 7212276}, {"name": "恐龙", "id": 74062}, {"name": "地理大发现", "id": 1205031}, {"name": "马克斯·沃夫发现的天体", "id": 3384986}, {"name": "约翰·帕利扎发现的天体", "id": 3414626}, {"name": "布雷特·J·格拉德曼发现的天体", "id": 7656118}, {"name": "威廉·赫歇尔发现的天体", "id": 8016988}, {"name": "约翰·赫歇尔发现的天体", "id": 8020361}, {"name": "小行星發現者", "id": 593141}, {"name": "彗星發現者", "id": 1168403}]}