{"name": "電腦硬件公司", "id": 207081, "predecessors": [{"name": "電腦硬體", "id": 460677}, {"name": "产业", "id": 58086}], "successors": [{"name": "冶天科技", "id": 519310}, {"name": "苹果公司", "id": 3149287}, {"name": "臺灣電腦硬體公司", "id": 5974855}, {"name": "英伟达", "id": 6313412}, {"name": "蘋果公司硬體", "id": 3212942}, {"name": "微軟硬體", "id": 4569426}, {"name": "Wii遊戲", "id": 348405}, {"name": "Wii_U遊戲", "id": 1753355}, {"name": "红白机游戏", "id": 132133}, {"name": "Game_Boy游戏", "id": 198454}, {"name": "任天堂64遊戲", "id": 345381}, {"name": "任天堂DS遊戲", "id": 345390}, {"name": "Game_Boy_Advance遊戲", "id": 345391}, {"name": "任天堂3DS游戏", "id": 1516296}, {"name": "任天堂GameCube游戏", "id": 2813081}, {"name": "超级任天堂游戏", "id": 2813180}, {"name": "Game_Boy_Color游戏", "id": 3177823}, {"name": "Nintendo_Network遊戲", "id": 3989517}, {"name": "任天堂Switch游戏", "id": 5488082}, {"name": "PC_Engine遊戲", "id": 1253374}]}