{"name": "计算机科学", "id": 326427, "predecessors": [{"name": "总览", "id": 6349075}, {"name": "虛構", "id": 69954}], "successors": [{"name": "人工智能", "id": 43170}, {"name": "软件工程", "id": 46038}, {"name": "信息论", "id": 291241}, {"name": "软件", "id": 322354}, {"name": "計算機算術", "id": 535711}, {"name": "人機互動", "id": 632385}, {"name": "计算语言学", "id": 899631}, {"name": "語義學", "id": 1035773}, {"name": "计算机错误", "id": 1168189}, {"name": "计算科学", "id": 1357745}, {"name": "计算机编程", "id": 1402830}, {"name": "網路遊戲", "id": 69119}, {"name": "電腦安全", "id": 65992}, {"name": "计算机图形学", "id": 124354}, {"name": "數學最佳化", "id": 1234093}, {"name": "学术的编程语言", "id": 7026683}]}