{"name": "伊斯兰教", "id": 33585, "predecessors": [{"name": "阿拉伯文化", "id": 680449}, {"name": "形上學理論", "id": 1180576}], "successors": [{"name": "伊斯蘭教歷史", "id": 1122294}, {"name": "伊斯蘭教術語", "id": 1149255}, {"name": "伊斯蘭教相關爭議", "id": 1244626}, {"name": "阿拉伯人", "id": 84690}, {"name": "阿拉伯文化", "id": 680449}, {"name": "阿拔斯王朝哈里发", "id": 5050418}, {"name": "古兰经人物", "id": 470275}, {"name": "古蘭經", "id": 759910}, {"name": "伊斯蘭建築", "id": 796691}, {"name": "蘇非主義", "id": 1149279}, {"name": "逊尼派穆斯林", "id": 2841614}, {"name": "巴以冲突", "id": 3171942}, {"name": "印度尼西亞穆斯林", "id": 1238499}, {"name": "法國穆斯林", "id": 1279272}, {"name": "印度穆斯林", "id": 1489295}, {"name": "蒙古帝国穆斯林", "id": 6854964}, {"name": "哈萨克汗国可汗", "id": 7365904}, {"name": "伊斯蘭聖戰組織", "id": 73495}, {"name": "台灣穆斯林", "id": 1684335}, {"name": "维吾尔族文化", "id": 1352075}, {"name": "穆斯林女性政治人物", "id": 7611764}, {"name": "維吾爾族運動員", "id": 8374980}, {"name": "中华人民共和国维吾尔族政治人物", "id": 1925410}, {"name": "中华民国大陆时期维吾尔族政治人物", "id": 6536050}, {"name": "中华人民共和国建立后的维吾尔族中国共产党党员", "id": 1925403}]}