{"name": "流行音樂類型", "id": 3888447, "predecessors": [{"name": "流行音樂", "id": 494036}, {"name": "声音", "id": 58289}], "successors": [{"name": "韓語流行音樂團體", "id": 1497714}, {"name": "華語流行音樂團體", "id": 1498314}, {"name": "粵語流行音樂團體", "id": 1498362}, {"name": "期間限定團體", "id": 5138784}, {"name": "已解散的男子演唱團體", "id": 489299}, {"name": "流行舞曲歌曲", "id": 3988446}, {"name": "日本男子演唱團體", "id": 476429}, {"name": "臺灣男子演唱團體", "id": 489291}, {"name": "香港男子演唱團體", "id": 524040}, {"name": "韓國男子演唱團體", "id": 907758}, {"name": "中国男子演唱团体", "id": 1056588}]}