{"name": "夏季奥林匹克运动会", "id": 40904, "predecessors": [{"name": "四年一度的體育事件", "id": 7718859}], "successors": [{"name": "夏季奥林匹克运动会比赛项目", "id": 519062}, {"name": "夏季奥林匹克运动会主办城市", "id": 578207}, {"name": "夏季奥林匹克运动会奖牌榜", "id": 925806}, {"name": "夏季奧林匹克運動會比賽項目模板", "id": 813647}, {"name": "奧運足球場館", "id": 5415149}, {"name": "英國奧運田徑運動員", "id": 4080730}, {"name": "牙買加奧運田徑運動員", "id": 4085046}, {"name": "衣索比亞奧運田徑運動員", "id": 4087773}, {"name": "美國奧運田徑運動員", "id": 4092322}, {"name": "波兰奥运田径运动员", "id": 5020868}, {"name": "荷兰奥运田径运动员", "id": 5021160}, {"name": "德国奥运田径运动员", "id": 5021208}, {"name": "加拿大奥运田径运动员", "id": 5023080}, {"name": "澳大利亚奥运田径运动员", "id": 5023135}, {"name": "中国奥运田径运动员", "id": 5023477}, {"name": "肯尼亚奥运田径运动员", "id": 5025481}, {"name": "日本奥运田径运动员", "id": 5028903}, {"name": "法国奥运田径运动员", "id": 6457872}, {"name": "古巴奥运田径运动员", "id": 6765895}, {"name": "意大利奥运田径运动员", "id": 6786738}, {"name": "南非奥运田径运动员", "id": 6788394}, {"name": "芬兰奥运田径运动员", "id": 6788492}, {"name": "罗马尼亚奥运田径运动员", "id": 6792136}, {"name": "新西兰奥运田径运动员", "id": 6792228}, {"name": "瑞典奥运田径运动员", "id": 6793200}, {"name": "东德奥运田径运动员", "id": 6794420}, {"name": "西班牙奥运田径运动员", "id": 6801249}, {"name": "匈牙利奥运田径运动员", "id": 7601484}, {"name": "西德奥运田径运动员", "id": 7846061}, {"name": "德国联队奥运田径运动员", "id": 7914459}, {"name": "美國奧運跳水運動員", "id": 4096975}, {"name": "德國奧運跳水運動員", "id": 5420287}, {"name": "中国奥运跳水运动员", "id": 6091910}, {"name": "墨西哥奥运跳水运动员", "id": 6783668}, {"name": "澳大利亚奥运跳水运动员", "id": 6783734}, {"name": "加拿大奥运跳水运动员", "id": 6784522}, {"name": "英国奥运跳水运动员", "id": 8023474}, {"name": "英國奧運自由車選手", "id": 4677502}, {"name": "中国奥运自行车运动员", "id": 6091907}, {"name": "东德奥运自行车运动员", "id": 7440257}, {"name": "德国奥运自行车运动员", "id": 7440268}, {"name": "荷兰奥运自行车运动员", "id": 7441569}, {"name": "意大利奥运自行车运动员", "id": 7607907}, {"name": "法国奥运自行车运动员", "id": 7608155}, {"name": "澳大利亚奥运自行车运动员", "id": 7608174}, {"name": "瑞典奥运自行车运动员", "id": 7616248}, {"name": "波兰奥运自行车运动员", "id": 7964312}, {"name": "日本奥运自行车运动员", "id": 8170894}, {"name": "加拿大奥运自行车运动员", "id": 8190594}, {"name": "新西兰奥运自行车运动员", "id": 8387191}, {"name": "中国奥运射箭运动员", "id": 6091800}, {"name": "意大利奥运射箭运动员", "id": 7594976}, {"name": "意大利奥运射击运动员", "id": 7600381}, {"name": "法国奥运射箭运动员", "id": 7636163}, {"name": "韩国奥运射箭运动员", "id": 8071367}, {"name": "中国奥运羽毛球运动员", "id": 6091888}, {"name": "英國奧運羽毛球運動員", "id": 6660524}, {"name": "馬來西亞奧運羽毛球運動員", "id": 6660529}, {"name": "印尼奧運羽毛球運動員", "id": 6660530}, {"name": "日本奧運羽毛球運動員", "id": 6660534}, {"name": "丹麥奧運羽毛球運動員", "id": 6660536}, {"name": "韓國奧運羽毛球運動員", "id": 6660538}, {"name": "韩国奥运棒球运动员", "id": 5735613}, {"name": "日本奧運棒球運動員", "id": 7581692}, {"name": "古巴奥运棒球运动员", "id": 8198844}, {"name": "法國奧運擊劍運動員", "id": 4324859}, {"name": "匈牙利奧運擊劍運動員", "id": 5409676}, {"name": "韓國奧運擊劍運動員", "id": 5420442}, {"name": "中国奥运击剑运动员", "id": 6091921}, {"name": "意大利奥运击剑运动员", "id": 6697490}, {"name": "德国奥运击剑运动员", "id": 6697491}, {"name": "美国奥运击剑运动员", "id": 6701814}, {"name": "俄罗斯奥运击剑运动员", "id": 6701815}, {"name": "罗马尼亚奥运击剑运动员", "id": 6701885}, {"name": "日本奥运击剑运动员", "id": 6702222}, {"name": "波兰奥运击剑运动员", "id": 7408294}, {"name": "苏联奥运击剑运动员", "id": 7408304}, {"name": "西德奥运击剑运动员", "id": 7409692}, {"name": "瑞典奥运击剑运动员", "id": 7414438}, {"name": "中国奥运射击运动员", "id": 6091967}, {"name": "美國奧運射擊運動員", "id": 7576995}, {"name": "瑞典奥运射击运动员", "id": 7616465}, {"name": "法国奥运射击运动员", "id": 7635563}, {"name": "英国奥运射击运动员", "id": 7636113}, {"name": "德国奥运射击运动员", "id": 7923315}, {"name": "澳大利亚奥运射击运动员", "id": 7956507}, {"name": "澳大利亚奥运游泳运动员", "id": 5075837}, {"name": "匈牙利奧運游泳運動員", "id": 5410093}, {"name": "法國奧運游泳運動員", "id": 5415310}, {"name": "義大利奧運游泳運動員", "id": 5419669}, {"name": "日本奥运游泳运动员", "id": 5498754}, {"name": "中国奥运游泳运动员", "id": 6091976}, {"name": "美国奥运游泳运动员", "id": 6801321}, {"name": "荷兰奥运游泳运动员", "id": 7246615}, {"name": "瑞典奥运游泳运动员", "id": 7616447}, {"name": "德国奥运游泳运动员", "id": 7662516}, {"name": "东德奥运游泳运动员", "id": 7847051}, {"name": "英国奥运游泳运动员", "id": 7907968}, {"name": "西德奥运游泳运动员", "id": 7909693}, {"name": "加拿大奥运游泳运动员", "id": 7945982}, {"name": "俄罗斯奥运游泳运动员", "id": 8182072}, {"name": "新西兰奥运游泳运动员", "id": 8186178}, {"name": "日本奧運柔道運動員", "id": 5427045}, {"name": "中国奥运柔道运动员", "id": 6091956}, {"name": "法国奥运柔道运动员", "id": 7647798}, {"name": "德国奥运柔道运动员", "id": 7985018}, {"name": "韩国奥运柔道运动员", "id": 8030581}, {"name": "巴西奥运柔道运动员", "id": 8180824}, {"name": "日本奧運網球運動員", "id": 5220321}, {"name": "捷克奧運網球運動員", "id": 5403124}, {"name": "中国奥运网球运动员", "id": 6091990}, {"name": "阿根廷奥运网球运动员", "id": 6801579}, {"name": "俄罗斯奥运网球运动员", "id": 6801590}, {"name": "美国奥运网球运动员", "id": 6801827}, {"name": "德国奥运网球运动员", "id": 6802307}, {"name": "西班牙奥运网球运动员", "id": 6803418}, {"name": "英国奥运网球运动员", "id": 6803564}, {"name": "法国奥运网球运动员", "id": 6803565}, {"name": "澳大利亚奥运网球运动员", "id": 6808944}, {"name": "意大利奥运网球运动员", "id": 7614046}, {"name": "法國奧運籃球運動員", "id": 5420573}, {"name": "塞爾維亞奧運籃球運動員", "id": 5420583}, {"name": "中国奥运篮球运动员", "id": 5679690}, {"name": "澳大利亚奥运篮球运动员", "id": 6432166}, {"name": "日本奥运篮球运动员", "id": 6490135}, {"name": "意大利奥运篮球运动员", "id": 6493747}, {"name": "西班牙奥运篮球运动员", "id": 6494191}, {"name": "美国奥运篮球运动员", "id": 6494224}, {"name": "克罗地亚奥运篮球运动员", "id": 6494264}, {"name": "乌拉圭奥运篮球运动员", "id": 6598171}, {"name": "韩国奥运篮球运动员", "id": 6604645}, {"name": "加拿大奥运篮球运动员", "id": 7451679}, {"name": "中華民國奧運籃球運動員", "id": 7976187}, {"name": "南斯拉夫奥运篮球运动员", "id": 8039869}, {"name": "古巴奧運拳擊運動員", "id": 5420460}, {"name": "美国奥运拳击运动员", "id": 6801314}, {"name": "意大利奥运拳击运动员", "id": 7608870}, {"name": "波兰奥运拳击运动员", "id": 7963093}, {"name": "英国奥运拳击运动员", "id": 8141384}, {"name": "日本奥运拳击运动员", "id": 8170812}, {"name": "澳大利亚奥运拳击运动员", "id": 8175073}, {"name": "瑞典奥运帆船运动员", "id": 7616851}, {"name": "挪威奥运帆船运动员", "id": 7635243}, {"name": "法国奥运帆船运动员", "id": 7647134}, {"name": "德国奥运帆船运动员", "id": 7662459}, {"name": "美国奥运帆船运动员", "id": 7947409}, {"name": "英国奥运帆船运动员", "id": 8141527}, {"name": "日本奥运帆船运动员", "id": 8171336}, {"name": "澳大利亚奥运帆船运动员", "id": 8175034}, {"name": "西班牙奥运帆船运动员", "id": 8180964}, {"name": "法國奧運手球運動員", "id": 5026910}, {"name": "克羅埃西亞奧運手球運動員", "id": 5026945}, {"name": "韓國奧運手球運動員", "id": 5885436}, {"name": "中国奥运手球运动员", "id": 6091953}, {"name": "瑞典奥运手球运动员", "id": 7616876}, {"name": "挪威奥运手球运动员", "id": 7635222}, {"name": "匈牙利奥运手球运动员", "id": 7641967}, {"name": "德国奥运手球运动员", "id": 7661976}, {"name": "东德奥运手球运动员", "id": 7910668}, {"name": "罗马尼亚奥运手球运动员", "id": 7957143}, {"name": "波兰奥运手球运动员", "id": 7966261}, {"name": "南斯拉夫奥运手球运动员", "id": 8044306}, {"name": "丹麦奥运手球运动员", "id": 8051129}, {"name": "西班牙奥运手球运动员", "id": 8074464}, {"name": "黑山奥运手球运动员", "id": 8121000}, {"name": "日本奧運體操運動員", "id": 5026956}, {"name": "中国奥运体操运动员", "id": 6091951}, {"name": "美国奥运体操运动员", "id": 6803542}, {"name": "罗马尼亚奥运体操运动员", "id": 6803796}, {"name": "瑞典奥运体操运动员", "id": 7423645}, {"name": "意大利奥运体操运动员", "id": 7424236}, {"name": "芬兰奥运体操运动员", "id": 7424367}, {"name": "瑞士奥运体操运动员", "id": 7425432}, {"name": "德国奥运体操运动员", "id": 7425465}, {"name": "挪威奥运体操运动员", "id": 7426643}, {"name": "英国奥运体操运动员", "id": 7427688}, {"name": "匈牙利奥运体操运动员", "id": 7428575}, {"name": "法国奥运体操运动员", "id": 7428639}, {"name": "东德奥运体操运动员", "id": 7430389}, {"name": "捷克斯洛伐克奥运体操运动员", "id": 7431385}, {"name": "丹麦奥运体操运动员", "id": 7432130}, {"name": "中国奥运乒乓球运动员", "id": 5894009}, {"name": "韩国奥运乒乓球运动员", "id": 7591635}, {"name": "美國奧運排球運動員", "id": 5249369}, {"name": "中国奥运排球运动员", "id": 6091993}, {"name": "日本奥运排球运动员", "id": 7117880}, {"name": "意大利奥运排球运动员", "id": 7489434}, {"name": "古巴奥运排球运动员", "id": 7591889}, {"name": "波兰奥运排球运动员", "id": 7963033}, {"name": "东德奥运排球运动员", "id": 7982497}, {"name": "塞尔维亚奥运排球运动员", "id": 8063606}, {"name": "阿根廷奥运排球运动员", "id": 8217039}, {"name": "美國奧運水球運動員", "id": 5249768}, {"name": "塞爾維亞奧運水球運動員", "id": 5451035}, {"name": "中国奥运水球运动员", "id": 6091994}, {"name": "意大利奥运水球运动员", "id": 6623147}, {"name": "匈牙利奥运水球运动员", "id": 6756838}, {"name": "澳大利亚奥运水球运动员", "id": 7589684}, {"name": "西班牙奥运水球运动员", "id": 7589725}, {"name": "德国奥运水球运动员", "id": 7661359}, {"name": "英国奥运水球运动员", "id": 7908669}, {"name": "南斯拉夫奥运水球运动员", "id": 8044244}, {"name": "黑山奥运水球运动员", "id": 8060391}, {"name": "克罗地亚奥运水球运动员", "id": 8060649}, {"name": "巴西奧運足球運動員", "id": 1203704}, {"name": "瑞典奧運足球運動員", "id": 5409320}, {"name": "德國奧運足球運動員", "id": 5415174}, {"name": "日本奧運足球運動員", "id": 5415190}, {"name": "墨西哥奧運足球運動員", "id": 5415197}, {"name": "韓國奧運足球運動員", "id": 5415235}, {"name": "中国奥运足球运动员", "id": 6091936}, {"name": "美国奥运足球运动员", "id": 6802038}, {"name": "阿根廷奥运足球运动员", "id": 6805450}, {"name": "西班牙奧運足球運動員", "id": 7560943}, {"name": "義大利奧運足球運動員", "id": 7561003}, {"name": "挪威奥运足球运动员", "id": 7635088}, {"name": "匈牙利奥运足球运动员", "id": 7637052}, {"name": "法国奥运足球运动员", "id": 7649390}, {"name": "东德奥运足球运动员", "id": 7938105}, {"name": "波兰奥运足球运动员", "id": 7962472}, {"name": "中華民國奧運足球運動員", "id": 7991469}, {"name": "丹麦奥运足球运动员", "id": 8012919}, {"name": "南斯拉夫奥运足球运动员", "id": 8034812}, {"name": "英国奥运足球运动员", "id": 8096099}, {"name": "加拿大奥运足球运动员", "id": 8098084}, {"name": "捷克斯洛伐克奥运足球运动员", "id": 8100426}, {"name": "日本奧運角力運動員", "id": 5478714}, {"name": "匈牙利奥运摔跤运动员", "id": 7601750}, {"name": "芬兰奥运摔跤运动员", "id": 7606529}, {"name": "意大利奥运摔跤运动员", "id": 7611321}, {"name": "瑞典奥运摔跤运动员", "id": 7616255}, {"name": "罗马尼亚奥运摔跤运动员", "id": 7954287}, {"name": "波兰奥运摔跤运动员", "id": 7963206}, {"name": "土耳其奥运摔跤运动员", "id": 8161383}, {"name": "美国奥运摔跤运动员", "id": 8169763}, {"name": "罗马尼亚奥运赛艇运动员", "id": 7600602}, {"name": "罗马尼亚奥运皮划艇运动员", "id": 7954671}, {"name": "波兰奥运赛艇运动员", "id": 7948484}, {"name": "波兰奥运举重运动员", "id": 7963023}, {"name": "波兰奥运皮划艇运动员", "id": 7964304}, {"name": "捷克斯洛伐克奥运赛艇运动员", "id": 7945818}, {"name": "印度奥运曲棍球运动员", "id": 8015208}, {"name": "巴基斯坦奥运曲棍球运动员", "id": 7597273}, {"name": "东德奥运皮划艇运动员", "id": 7662159}, {"name": "东德奥运赛艇运动员", "id": 7940445}, {"name": "西德奥运马术运动员", "id": 7662529}, {"name": "西德奥运赛艇运动员", "id": 7909737}, {"name": "西德奥运曲棍球运动员", "id": 7917553}, {"name": "2008年夏季奧林匹克運動會", "id": 353970}, {"name": "2020年夏季奧林匹克運動會", "id": 3444645}, {"name": "2012年夏季奥林匹克运动会足球运动员", "id": 2937600}, {"name": "2012年夏季奧林匹克運動會獎牌得主", "id": 4085067}, {"name": "2012年夏季奧林匹克運動會田徑運動員", "id": 4085079}, {"name": "2012年夏季奧林匹克運動會射箭運動員", "id": 4103855}, {"name": "2012年夏季奧林匹克運動會羽球運動員", "id": 4104841}, {"name": "2012年夏季奧林匹克運動會擊劍運動員", "id": 4107104}, {"name": "2012年夏季奧林匹克運動會划船運動員", "id": 4230644}, {"name": "2012年夏季奧林匹克運動會舉重運動員", "id": 4235041}, {"name": "2012年夏季奧林匹克運動會自由車選手", "id": 4241326}, {"name": "2012年夏季奧林匹克運動會射擊運動員", "id": 4246385}, {"name": "2012年夏季奧林匹克運動會游泳運動員", "id": 4249608}, {"name": "2012年夏季奧林匹克運動會網球運動員", "id": 4274158}, {"name": "2012年夏季奧林匹克運動會跆拳道運動員", "id": 4277275}, {"name": "2012年夏季奧林匹克運動會柔道運動員", "id": 4277724}, {"name": "2012年夏季奧林匹克運動會籃球運動員", "id": 5022013}, {"name": "2012年夏季奧林匹克運動會拳擊運動員", "id": 5022043}, {"name": "2012年夏季奧林匹克運動會跳水運動員", "id": 5026163}, {"name": "2012年夏季奧林匹克運動會帆船運動員", "id": 5026455}, {"name": "2012年夏季奧林匹克運動會輕艇運動員", "id": 5026536}, {"name": "2012年夏季奧林匹克運動會手球運動員", "id": 5026901}, {"name": "2012年夏季奧林匹克運動會體操運動員", "id": 5026963}, {"name": "2012年夏季奧林匹克運動會桌球運動員", "id": 5220077}, {"name": "2012年夏季奧林匹克運動會排球運動員", "id": 5249222}, {"name": "2012年夏季奧林匹克運動會水球運動員", "id": 5249732}, {"name": "2012年夏季奧林匹克運動會角力運動員", "id": 5420872}, {"name": "2012年夏季奧林匹克運動會曲棍球運動員", "id": 5451703}, {"name": "2012年夏季奧林匹克運動會鐵人三項運動員", "id": 5476777}, {"name": "2012年夏季奥林匹克运动会花样游泳运动员", "id": 7592038}, {"name": "2012年夏季奥林匹克运动会马术运动员", "id": 7623231}, {"name": "2016年夏季奧林匹克運動會帆船運動員", "id": 5402156}, {"name": "2016年夏季奥林匹克运动会乒乓球运动员", "id": 5402182}, {"name": "2016年夏季奧林匹克運動會田徑運動員", "id": 5403238}, {"name": "2016年夏季奧林匹克運動會游泳運動員", "id": 5403261}, {"name": "2016年夏季奧林匹克運動會射箭運動員", "id": 5408458}, {"name": "2016年夏季奧林匹克運動會自由車選手", "id": 5408696}, {"name": "2016年夏季奧林匹克運動會足球運動員", "id": 5409324}, {"name": "2016年夏季奧林匹克運動會手球運動員", "id": 5409465}, {"name": "2016年夏季奧林匹克運動會射擊運動員", "id": 5409540}, {"name": "2016年夏季奧林匹克運動會獎牌得主", "id": 5409543}, {"name": "2016年夏季奧林匹克運動會擊劍運動員", "id": 5409673}, {"name": "2016年夏季奧林匹克運動會羽毛球運動員", "id": 5409744}, {"name": "2016年夏季奧林匹克運動會跳水運動員", "id": 5409828}, {"name": "2016年夏季奧林匹克運動會柔道運動員", "id": 5409837}, {"name": "2016年夏季奧林匹克運動會體操運動員", "id": 5409839}, {"name": "2016年夏季奥林匹克运动会举重运动员", "id": 5412375}, {"name": "2016年夏季奧林匹克運動會角力運動員", "id": 5415081}, {"name": "2016年夏季奧林匹克運動會輕艇運動員", "id": 5420224}, {"name": "2016年夏季奧林匹克運動會拳擊運動員", "id": 5420465}, {"name": "2016年夏季奧林匹克運動會水球運動員", "id": 5420483}, {"name": "2016年夏季奧林匹克運動會高爾夫運動員", "id": 5420489}, {"name": "2016年夏季奧林匹克運動會七人制橄欖球運動員", "id": 5420511}, {"name": "2016年夏季奧林匹克運動會划船運動員", "id": 5420545}, {"name": "2016年夏季奧林匹克運動會籃球運動員", "id": 5420571}, {"name": "2016年夏季奥林匹克运动会排球运动员", "id": 5422263}, {"name": "2016年夏季奥林匹克运动会网球运动员", "id": 5432690}, {"name": "2016年夏季奧林匹克運動會跆拳道運動員", "id": 5447932}, {"name": "2016年夏季奧林匹克運動會曲棍球運動員", "id": 5451700}, {"name": "2016年夏季奧林匹克運動會鐵人三項運動員", "id": 5476771}, {"name": "2016年夏季奧林匹克運動會現代五項運動員", "id": 5477309}, {"name": "2016年夏季奥林匹克运动会花样游泳运动员", "id": 7592040}, {"name": "2016年夏季奥林匹克运动会马术运动员", "id": 7621336}, {"name": "1932年夏季奧林匹克運動會獎牌得主", "id": 5256103}, {"name": "1932年夏季奥林匹克运动会田径运动员", "id": 5415074}, {"name": "1932年夏季奥林匹克运动会击剑运动员", "id": 6629659}, {"name": "1932年夏季奥林匹克运动会游泳运动员", "id": 6629675}, {"name": "1932年夏季奥林匹克运动会水球运动员", "id": 6697000}, {"name": "1932年夏季奥林匹克运动会体操运动员", "id": 7424347}, {"name": "1932年夏季奥林匹克运动会赛艇运动员", "id": 7602828}, {"name": "1932年夏季奥林匹克运动会摔跤运动员", "id": 7606739}, {"name": "1936年夏季奥林匹克运动会摔跤运动员", "id": 7606740}, {"name": "1932年夏季奥林匹克运动会自行车运动员", "id": 7608131}, {"name": "1932年夏季奥林匹克运动会帆船运动员", "id": 7621328}, {"name": "1936年夏季奧林匹克運動會獎牌得主", "id": 5256108}, {"name": "1936年夏季奥林匹克运动会田径运动员", "id": 5415075}, {"name": "1936年夏季奥林匹克运动会篮球运动员", "id": 5415316}, {"name": "1936年夏季奧林匹克運動會足球運動員", "id": 5504612}, {"name": "1936年夏季奥林匹克运动会击剑运动员", "id": 6629660}, {"name": "1936年夏季奥林匹克运动会游泳运动员", "id": 6629689}, {"name": "1936年夏季奥林匹克运动会体操运动员", "id": 7424355}, {"name": "1936年夏季奥林匹克运动会水球运动员", "id": 7437106}, {"name": "1936年夏季奥林匹克运动会赛艇运动员", "id": 7602829}, {"name": "1936年夏季奥林匹克运动会自行车运动员", "id": 7608132}, {"name": "1936年夏季奥林匹克运动会帆船运动员", "id": 7609793}, {"name": "1936年夏季奥林匹克运动会皮划艇运动员", "id": 7616242}, {"name": "1936年夏季奥林匹克运动会马术运动员", "id": 7623144}, {"name": "1936年夏季奥林匹克运动会室外手球运动员", "id": 7662521}, {"name": "1936年夏季奥林匹克运动会曲棍球运动员", "id": 7920153}, {"name": "1924年夏季奧林匹克運動會獎牌得主", "id": 5256085}, {"name": "1924年夏季奥林匹克运动会赛艇运动员", "id": 5421044}, {"name": "1924年夏季奥林匹克运动会足球运动员", "id": 6629234}, {"name": "1924年夏季奥林匹克运动会田径运动员", "id": 6629243}, {"name": "1924年夏季奥林匹克运动会网球运动员", "id": 6629266}, {"name": "1924年夏季奥林匹克运动会摔跤运动员", "id": 6629268}, {"name": "1924年夏季奥林匹克运动会游泳运动员", "id": 6629275}, {"name": "1924年夏季奥林匹克运动会水球运动员", "id": 6629276}, {"name": "1924年夏季奥林匹克运动会击剑运动员", "id": 6699462}, {"name": "1924年夏季奥林匹克运动会体操运动员", "id": 7424271}, {"name": "1924年夏季奥林匹克运动会射击运动员", "id": 7426720}, {"name": "1924年夏季奥林匹克运动会马术运动员", "id": 7608751}, {"name": "1924年夏季奥林匹克运动会橄榄球运动员", "id": 7653419}, {"name": "1960年夏季奧林匹克運動會獎牌得主", "id": 5257985}, {"name": "1960年夏季奥林匹克运动会游泳运动员", "id": 5468167}, {"name": "1960年夏季奥林匹克运动会篮球运动员", "id": 6433496}, {"name": "1960年夏季奥林匹克运动会水球运动员", "id": 6623141}, {"name": "1960年夏季奥林匹克运动会体操运动员", "id": 6628413}, {"name": "1960年夏季奥林匹克运动会帆船运动员", "id": 6629643}, {"name": "1960年夏季奥林匹克运动会击剑运动员", "id": 6629664}, {"name": "1960年夏季奥林匹克运动会田径运动员", "id": 6765340}, {"name": "1960年夏季奧林匹克運動會拳擊運動員", "id": 6780543}, {"name": "1960年夏季奥林匹克运动会曲棍球运动员", "id": 7596750}, {"name": "1960年夏季奥林匹克运动会赛艇运动员", "id": 7600963}, {"name": "1960年夏季奥林匹克运动会摔跤运动员", "id": 7606751}, {"name": "1960年夏季奥林匹克运动会自行车运动员", "id": 7607906}, {"name": "1960年夏季奥林匹克运动会马术运动员", "id": 7611172}, {"name": "1960年夏季奥林匹克运动会皮划艇运动员", "id": 7612416}, {"name": "1960年夏季奥林匹克运动会足球运动员", "id": 7637762}, {"name": "1896年夏季奧林匹克運動會獎牌得主", "id": 4023176}, {"name": "1896年夏季奥林匹克运动会田径运动员", "id": 6628425}, {"name": "1920年夏季奧林匹克運動會獎牌得主", "id": 642055}, {"name": "1984年夏季奧林匹克運動會獎牌得主", "id": 1863975}, {"name": "1992年夏季奧林匹克運動會獎牌得主", "id": 1863977}, {"name": "1908年夏季奧林匹克運動會獎牌得主", "id": 3937875}, {"name": "2008年夏季奧林匹克運動會獎牌得主", "id": 4085069}, {"name": "2004年夏季奧林匹克運動會獎牌得主", "id": 4086639}, {"name": "1988年夏季奧林匹克運動會獎牌得主", "id": 4096204}, {"name": "1996年夏季奧林匹克運動會獎牌得主", "id": 4096207}, {"name": "1976年夏季奧林匹克運動會獎牌得主", "id": 4097437}, {"name": "2000年夏季奥林匹克运动会奖牌得主", "id": 5025461}, {"name": "1900年夏季奧林匹克運動會獎牌得主", "id": 5255713}, {"name": "1928年夏季奧林匹克運動會獎牌得主", "id": 5256093}, {"name": "1980年夏季奧林匹克運動會獎牌得主", "id": 5257376}, {"name": "1972年夏季奧林匹克運動會獎牌得主", "id": 5257407}, {"name": "1968年夏季奧林匹克運動會獎牌得主", "id": 5257580}, {"name": "1964年夏季奧林匹克運動會獎牌得主", "id": 5257701}, {"name": "1956年夏季奧林匹克運動會獎牌得主", "id": 5258008}, {"name": "1952年夏季奧林匹克運動會獎牌得主", "id": 5258021}, {"name": "1948年夏季奧林匹克運動會獎牌得主", "id": 5258028}, {"name": "1904年夏季奥林匹克运动会奖牌得主", "id": 6628605}, {"name": "1912年夏季奥林匹克运动会奖牌得主", "id": 6698348}, {"name": "2020年夏季奧林匹克運動會獎牌得主", "id": 7575177}, {"name": "2024年夏季奧林匹克運動會獎牌得主", "id": 8813512}, {"name": "1920年夏季奥林匹克运动会足球运动员", "id": 6629236}, {"name": "1920年夏季奥林匹克运动会田径运动员", "id": 6629241}, {"name": "1920年夏季奥林匹克运动会射击运动员", "id": 6629253}, {"name": "1920年夏季奥林匹克运动会游泳运动员", "id": 6693270}, {"name": "1920年夏季奥林匹克运动会水球运动员", "id": 6694070}, {"name": "1920年夏季奥林匹克运动会击剑运动员", "id": 6698331}, {"name": "1920年夏季奥林匹克运动会曲棍球运动员", "id": 7414878}, {"name": "1920年夏季奥林匹克运动会体操运动员", "id": 7424237}, {"name": "1920年夏季奥林匹克运动会赛艇运动员", "id": 7601367}, {"name": "1920年夏季奥林匹克运动会摔跤运动员", "id": 7606530}, {"name": "1920年夏季奥林匹克运动会帆船运动员", "id": 7617462}, {"name": "1920年夏季奥林匹克运动会冰球运动员", "id": 8103586}, {"name": "2020年夏季奧林匹克運動會壘球運動員", "id": 7557653}, {"name": "2020年夏季奧林匹克運動會足球運動員", "id": 7560938}, {"name": "2020年夏季奧林匹克運動會射箭運動員", "id": 7573590}, {"name": "2020年夏季奧林匹克運動會划船運動員", "id": 7573663}, {"name": "2020年夏季奧林匹克運動會羽毛球運動員", "id": 7574286}, {"name": "2020年夏季奧林匹克運動會射擊運動員", "id": 7574771}, {"name": "2020年夏季奧林匹克運動會擊劍運動員", "id": 7574949}, {"name": "2020年夏季奧林匹克運動會跆拳道運動員", "id": 7575128}, {"name": "2020年夏季奧林匹克運動會舉重運動員", "id": 7575342}, {"name": "2020年夏季奧林匹克運動會柔道運動員", "id": 7575552}, {"name": "2020年夏季奧林匹克運動會乒乓球運動員", "id": 7575905}, {"name": "2020年夏季奧林匹克運動會體操運動員", "id": 7576163}, {"name": "2020年夏季奧林匹克運動會游泳運動員", "id": 7576235}, {"name": "2020年夏季奧林匹克運動會排球運動員", "id": 7576491}, {"name": "2020年夏季奧林匹克運動會籃球運動員", "id": 7576903}, {"name": "2020年夏季奧林匹克運動會自由車選手", "id": 7577054}, {"name": "2020年夏季奧林匹克運動會高爾夫運動員", "id": 7578068}, {"name": "2020年夏季奧林匹克運動會輕艇運動員", "id": 7579803}, {"name": "2020年夏季奧林匹克運動會跳水運動員", "id": 7579809}, {"name": "2020年夏季奥林匹克运动会水球运动员", "id": 7580471}, {"name": "2020年夏季奧林匹克運動會棒球選手", "id": 7581699}, {"name": "2020年夏季奧林匹克運動會拳擊運動員", "id": 7583876}, {"name": "2020年夏季奧林匹克運動會田徑運動員", "id": 7584658}, {"name": "2020年夏季奧林匹克運動會網球運動員", "id": 7584701}, {"name": "2020年夏季奧林匹克運動會鐵人三項運動員", "id": 7585247}, {"name": "2020年夏季奧林匹克運動會帆船運動員", "id": 7585671}, {"name": "2020年夏季奧林匹克運動會角力運動員", "id": 7587131}, {"name": "2020年夏季奥林匹克运动会花样游泳运动员", "id": 7591727}, {"name": "2020年夏季奧林匹克運動會空手道運動員", "id": 7593122}, {"name": "2020年夏季奧林匹克運動會運動攀登運動員", "id": 7593440}, {"name": "2020年夏季奧林匹克運動會現代五項運動員", "id": 7594598}, {"name": "2020年夏季奧林匹克運動會曲棍球運動員", "id": 7594655}, {"name": "2020年夏季奥林匹克运动会马术运动员", "id": 7621337}, {"name": "2020年夏季奧林匹克運動會七人制橄欖球運動員", "id": 7634443}, {"name": "2020年夏季奥林匹克运动会手球运动员", "id": 7649465}, {"name": "德国联队奥运赛艇运动员", "id": 7941502}, {"name": "2024年夏季奥林匹克运动会比赛项目导航模版", "id": 8289570}, {"name": "加拿大奥运赛艇运动员", "id": 7943938}, {"name": "加拿大奥运皮划艇运动员", "id": 7977219}]}