{"name": "学校", "id": 41486, "predecessors": [{"name": "學校教育", "id": 1065124}, {"name": "公共行政", "id": 513495}, {"name": "建築物", "id": 3231846}, {"name": "維基百科管理", "id": 501839}], "successors": [{"name": "學校教育", "id": 1065124}, {"name": "歐洲大學列表", "id": 3461605}, {"name": "青岛已关闭学校", "id": 6115677}, {"name": "香港已關閉小學", "id": 1480175}, {"name": "香港已關閉中學", "id": 1480401}, {"name": "藝術學校背景作品", "id": 3611596}, {"name": "外国语学校", "id": 976287}, {"name": "外語院校", "id": 5469503}, {"name": "虛構專校背景作品", "id": 3611722}, {"name": "中华人民共和国高等院校的附属学校", "id": 6844380}, {"name": "中华人民共和国原铁路系统学校", "id": 7347143}, {"name": "中华人民共和国省部共建制高等院校", "id": 3492950}, {"name": "江苏省重点中学", "id": 1767301}, {"name": "浙江省一级重点中学", "id": 3186911}, {"name": "陕西省普通高中示范性学校", "id": 1689677}, {"name": "上海市实验性示范性高中", "id": 2813874}, {"name": "辽宁省省级示范性普通高中", "id": 2882666}, {"name": "河南省示范性普通高中", "id": 3023313}, {"name": "北京示范性高中", "id": 3492276}, {"name": "安徽示范性高中", "id": 3514399}, {"name": "四川示范性高中", "id": 3514495}, {"name": "河北示范性高中", "id": 3514514}, {"name": "湖北省示范中学", "id": 5088576}, {"name": "湖南省示范性普通高级中学", "id": 6206931}, {"name": "云南省一级普通高级中学", "id": 8091462}, {"name": "中国体育高校", "id": 3772131}, {"name": "各国高校导航模板", "id": 3759982}, {"name": "世界大學運動會導航模板", "id": 4031966}, {"name": "大学联盟导航模板", "id": 5500526}, {"name": "广东高等院校导航模板", "id": 7316288}, {"name": "學院科系", "id": 106523}, {"name": "大学排名", "id": 1113724}, {"name": "大学标志", "id": 945575}, {"name": "歐洲大學聯盟", "id": 4010376}, {"name": "国际大学联盟", "id": 5424150}, {"name": "大学和学院建立者", "id": 6949029}, {"name": "大學背景電視劇", "id": 1710065}, {"name": "大学背景电影", "id": 3337765}, {"name": "大學背景漫畫", "id": 4660396}, {"name": "理工院校", "id": 5469516}, {"name": "建築院校", "id": 5469549}, {"name": "財經院校", "id": 5469581}, {"name": "國際關係學校", "id": 6773989}, {"name": "日本的女子短期大学", "id": 3087273}, {"name": "畢業歌曲", "id": 1396137}, {"name": "台灣學校列表", "id": 608850}, {"name": "上海交通大学", "id": 564007}, {"name": "北京交通大学", "id": 1482661}, {"name": "西安交通大学", "id": 1630091}, {"name": "交通大学校友", "id": 3248909}, {"name": "國立交通大學教授", "id": 1502720}, {"name": "上海交通大学教授", "id": 3218431}, {"name": "西安交通大学教授", "id": 3257305}, {"name": "北京交通大學教授", "id": 3257342}, {"name": "西南交通大学教授", "id": 3295098}, {"name": "國立臺灣大學醫學院校友", "id": 4091267}, {"name": "哈佛医学院校友", "id": 5003221}, {"name": "哈佛商學院校友", "id": 4551940}, {"name": "宾夕法尼亚大学沃顿商学院校友", "id": 5316963}, {"name": "麻省理工学院斯隆管理学院校友", "id": 6408500}, {"name": "首尔大学法科大学校友", "id": 1783049}, {"name": "國立臺灣大學法律學院校友", "id": 5986555}, {"name": "哈佛法學院校友", "id": 4730046}, {"name": "哥伦比亚法学院校友", "id": 5694922}, {"name": "乔治城大学法律中心校友", "id": 6567960}, {"name": "河海大学校友", "id": 940005}, {"name": "中国海洋大学教授", "id": 3219728}, {"name": "日本的公立大學", "id": 1077396}, {"name": "美國公立大學", "id": 1476378}, {"name": "都柏林大学学院校友", "id": 3156966}, {"name": "日本短期大學", "id": 1781541}, {"name": "美国陆军指挥参谋学院校友", "id": 2975455}, {"name": "法國美術學院校友", "id": 6053223}, {"name": "伊頓公學校友", "id": 1527772}, {"name": "拉格比公學校友", "id": 4102396}, {"name": "查特豪斯公學校友", "id": 5381687}, {"name": "温彻斯特公学校友", "id": 5653826}, {"name": "龙校校友", "id": 5298011}, {"name": "英華中學校友", "id": 1576481}, {"name": "新加坡國立大學校友", "id": 554348}, {"name": "南洋理工大學校友", "id": 1493331}, {"name": "中華民國大專院校的附設學校", "id": 6843669}, {"name": "海軍大學校校友", "id": 6769249}, {"name": "駒澤大學校友", "id": 3788413}, {"name": "東國大學校友", "id": 1048167}, {"name": "愛丁堡大學校友", "id": 554234}, {"name": "格拉斯哥大學校友", "id": 1266779}, {"name": "聖安德魯斯大學校友", "id": 1567451}, {"name": "阿伯丁大学校友", "id": 1674425}, {"name": "都柏林三一学院校友", "id": 3156973}, {"name": "臺北市立成功高級中學校友", "id": 269797}, {"name": "國立新竹高級中學校友", "id": 270296}, {"name": "臺北市立建國高級中學校友", "id": 339962}, {"name": "高雄市立高雄高級中學校友", "id": 365783}, {"name": "國立宜蘭高級中學校友", "id": 632319}, {"name": "國立花蓮高級中學校友", "id": 749309}, {"name": "國立屏東高級中學校友", "id": 3334392}, {"name": "國立臺南第一高級中學校友", "id": 4425980}, {"name": "臺灣省立嘉義中學校友", "id": 8202426}, {"name": "國立臺中第一高級中學校友", "id": 560209}, {"name": "臺中州立臺中第一中學校校友", "id": 5987995}, {"name": "臺灣省立臺中第一高級中學校友", "id": 5988018}, {"name": "国家示范性高等职业院校", "id": 7424144}, {"name": "美国大学篮球奖项导航模板", "id": 6215783}, {"name": "中华民国大陆时期校长", "id": 7284365}, {"name": "香港中學校長", "id": 235841}, {"name": "北京大学校长", "id": 1300166}, {"name": "北京交通大学校长", "id": 1492071}, {"name": "北京大学副校长", "id": 3252339}, {"name": "布里斯托老维克剧场学院校友", "id": 8512364}, {"name": "伏龍芝軍事學院校友", "id": 1726487}, {"name": "苏联总参军事学院校友", "id": 6658359}, {"name": "台灣特殊學校", "id": 613138}, {"name": "臺灣原住民實驗教育與重點學校", "id": 7482242}, {"name": "台灣天主教會學校", "id": 498328}, {"name": "臺灣學校型態實驗教育學校", "id": 7771072}, {"name": "國立體育大學籃球隊球員", "id": 7956751}, {"name": "杜克大學藍魔鬼男子籃球隊球員", "id": 8029733}, {"name": "肯塔基大學野貓男子籃球隊球員", "id": 8029855}, {"name": "加州大學洛杉磯分校棕熊男子籃球隊球員", "id": 8029876}, {"name": "加利福尼亞金熊男子籃球隊球員", "id": 8029923}, {"name": "維拉諾瓦大學野貓男子籃球隊球員", "id": 8032167}, {"name": "密蘇里大學老虎男子籃球隊球員", "id": 8037805}, {"name": "世界大学生运动会篮球奖牌得主", "id": 8041599}, {"name": "御茶水女子大學校友", "id": 1546696}, {"name": "臺灣繁星計劃大學", "id": 4986313}, {"name": "高等教育深耕計畫", "id": 6056103}, {"name": "臺灣大專院校整併", "id": 5784300}, {"name": "俄罗斯大学", "id": 114125}, {"name": "輔仁大學名譽博士", "id": 3444759}, {"name": "國立臺灣大學維基人", "id": 229266}, {"name": "國立交通大學維基人", "id": 236531}, {"name": "國立政治大學維基人", "id": 274073}, {"name": "世新大學維基人", "id": 275070}, {"name": "國立成功大學維基人", "id": 278546}, {"name": "國立中正大學維基人", "id": 284465}, {"name": "國立清華大學維基人", "id": 291918}, {"name": "國立中央大學維基人", "id": 335513}, {"name": "輔仁大學維基人", "id": 372364}, {"name": "國立臺灣師範大學維基人", "id": 656003}, {"name": "國立暨南國際大學維基人", "id": 1420962}, {"name": "台灣大專院校用戶框模板", "id": 6175728}, {"name": "越南大學", "id": 506195}, {"name": "國立中央大學教授", "id": 1242382}, {"name": "國立中央大學大陸時期教師", "id": 3716819}, {"name": "韓國私立大學", "id": 1611128}, {"name": "輔仁大學教授", "id": 3445779}, {"name": "卡迪夫大學校友", "id": 527082}, {"name": "威尔士大学校友", "id": 3518498}, {"name": "兽医院校", "id": 7615709}, {"name": "帕森設計學院校友", "id": 1456209}, {"name": "各国高校列表", "id": 5923581}, {"name": "武汉大学校史", "id": 3160565}, {"name": "北京大学校史", "id": 5643730}, {"name": "杭州大学校友", "id": 3248891}, {"name": "杭州大学教授", "id": 3248894}, {"name": "浙江农业大学校友", "id": 3292313}, {"name": "國立臺灣大學校史", "id": 5576378}, {"name": "梅竹賽", "id": 6080608}, {"name": "東京帝國大學校友", "id": 4703581}, {"name": "臺北市立體育學院校友", "id": 897273}, {"name": "國立交通大學校友", "id": 210071}, {"name": "國立陽明大學校友", "id": 1737319}, {"name": "銘傳大學校友", "id": 1045743}, {"name": "國立臺北大學校友", "id": 400949}, {"name": "國立臺北大學教授", "id": 1567667}, {"name": "國防大學政治作戰學院校友", "id": 1203607}, {"name": "澳門學校", "id": 232989}, {"name": "上海学校", "id": 2891292}, {"name": "香港大專院校", "id": 52590}, {"name": "香港特殊學校", "id": 337149}, {"name": "香港私立學校", "id": 510651}, {"name": "香港直資學校", "id": 511122}, {"name": "香港補助學校議會", "id": 743773}, {"name": "香港一條龍學校", "id": 1314040}, {"name": "香港學校列表", "id": 3221684}, {"name": "香港官立小學", "id": 611780}, {"name": "香港官立中學", "id": 650923}, {"name": "香港英文授課中學", "id": 5350868}, {"name": "香港中學教師", "id": 7701656}, {"name": "葵青區中學", "id": 1106628}, {"name": "東區中學_(香港)", "id": 1106683}, {"name": "元朗區中學", "id": 1106703}, {"name": "九龍城區中學", "id": 1106709}, {"name": "觀塘區中學", "id": 1106726}, {"name": "沙田區中學", "id": 1106809}, {"name": "深水埗區中學", "id": 1106840}, {"name": "西貢區中學", "id": 1106861}, {"name": "屯門區中學", "id": 1106887}, {"name": "黃大仙區中學", "id": 1106892}, {"name": "香港聖公會小學", "id": 3927417}, {"name": "天津高等院校", "id": 202112}, {"name": "天津中等学校", "id": 4753890}, {"name": "屯門區小學", "id": 1280998}, {"name": "東區小學_(香港)", "id": 1479956}, {"name": "深水埗區小學", "id": 1479983}, {"name": "九龍城區小學", "id": 1479996}, {"name": "黃大仙區小學", "id": 1480020}, {"name": "觀塘區小學", "id": 1480031}, {"name": "沙田區小學", "id": 1480051}, {"name": "元朗區小學", "id": 1480067}, {"name": "北京高等院校", "id": 98765}, {"name": "海淀区学校", "id": 4002856}, {"name": "重庆高等院校", "id": 202145}, {"name": "保良局學校", "id": 5049626}, {"name": "中華基督教會中學", "id": 5046568}, {"name": "重庆市南开中学校友", "id": 5592139}, {"name": "香港聖公會中學", "id": 3342470}, {"name": "莫斯科中山大学校友", "id": 1268785}, {"name": "国际列宁学校校友", "id": 3640083}, {"name": "莫斯科东方大学校友", "id": 3640108}, {"name": "鮑曼莫斯科國立技術大學校友", "id": 5235160}, {"name": "红色教授学院校友", "id": 6566485}]}