{"name": "语言学家", "id": 44471, "predecessors": [{"name": "总览", "id": 6349075}], "successors": [{"name": "字词典编纂者", "id": 599829}, {"name": "德国语言学家", "id": 36576}, {"name": "法国语言学家", "id": 56955}, {"name": "中国语言学家", "id": 70757}, {"name": "日本语言学家", "id": 90035}, {"name": "美国语言学家", "id": 90042}, {"name": "英国语言学家", "id": 430871}, {"name": "俄罗斯语言学家", "id": 1426223}, {"name": "中華民國語言學家", "id": 1459876}, {"name": "中国翻译家", "id": 81767}, {"name": "日本翻译家", "id": 476856}, {"name": "台灣翻譯家", "id": 748460}, {"name": "美国翻译家", "id": 1182282}, {"name": "中華民國翻譯家", "id": 1442537}, {"name": "法国翻译家", "id": 1669396}, {"name": "文字發明者", "id": 259252}, {"name": "中國漢字學家", "id": 5157648}, {"name": "20世纪翻译家", "id": 5463789}, {"name": "21世纪翻译家", "id": 5463790}, {"name": "19世纪翻译家", "id": 5463793}, {"name": "20世纪语文学家", "id": 7889734}, {"name": "佛经翻译家", "id": 1757014}, {"name": "聖經翻譯者", "id": 4497978}]}