{"name": "18世纪各年", "id": 456992, "predecessors": [{"name": "曆法", "id": 45146}, {"name": "年代学", "id": 454712}], "successors": [{"name": "1763年出生", "id": 80448}, {"name": "1763年逝世", "id": 92441}, {"name": "1749年出生", "id": 80672}, {"name": "1749年逝世", "id": 92429}, {"name": "1791年逝世", "id": 68299}, {"name": "1791年出生", "id": 81604}, {"name": "1736年出生", "id": 82333}, {"name": "1736年逝世", "id": 92461}, {"name": "1772年出生", "id": 82567}, {"name": "1772年逝世", "id": 92415}, {"name": "1771年出生", "id": 82586}, {"name": "1771年逝世", "id": 92411}, {"name": "1766年出生", "id": 84622}, {"name": "1766年逝世", "id": 88593}, {"name": "1743年出生", "id": 68055}, {"name": "1743年逝世", "id": 92420}, {"name": "1759年逝世", "id": 68277}, {"name": "1759年出生", "id": 84615}, {"name": "1716年出生", "id": 84476}, {"name": "1716年逝世", "id": 92454}, {"name": "1762年逝世", "id": 68291}, {"name": "1762年出生", "id": 84619}, {"name": "1787年出生", "id": 84636}, {"name": "1787年逝世", "id": 92403}, {"name": "1703年逝世", "id": 68176}, {"name": "1703年出生", "id": 84468}, {"name": "1750年逝世", "id": 68278}, {"name": "1750年出生", "id": 84612}, {"name": "1751年出生", "id": 68054}, {"name": "1751年逝世", "id": 92465}, {"name": "1752年逝世", "id": 66798}, {"name": "1752年出生", "id": 74399}, {"name": "1754年出生", "id": 68313}, {"name": "1754年逝世", "id": 92469}, {"name": "1755年逝世", "id": 68263}, {"name": "1755年出生", "id": 84613}, {"name": "1776年出生", "id": 84627}, {"name": "1776年逝世", "id": 92423}, {"name": "1799年逝世", "id": 68071}, {"name": "1799年出生", "id": 75148}, {"name": "1747年出生", "id": 84610}, {"name": "1747年逝世", "id": 92426}, {"name": "1798年出生", "id": 84641}, {"name": "1798年逝世", "id": 92414}, {"name": "1797年出生", "id": 70305}, {"name": "1797年逝世", "id": 92412}, {"name": "1707年出生", "id": 68297}, {"name": "1707年逝世", "id": 92436}, {"name": "1796年出生", "id": 68311}, {"name": "1796年逝世", "id": 68316}, {"name": "1706年出生", "id": 84470}, {"name": "1706年逝世", "id": 92433}, {"name": "1742年出生", "id": 84606}, {"name": "1704年出生", "id": 66797}, {"name": "1704年逝世", "id": 68284}, {"name": "1740年逝世", "id": 68280}, {"name": "1740年出生", "id": 68318}, {"name": "1795年出生", "id": 68048}, {"name": "1795年逝世", "id": 92410}, {"name": "1702年出生", "id": 73405}, {"name": "1702年逝世", "id": 92428}, {"name": "1790年出生", "id": 68049}, {"name": "1790年逝世", "id": 92409}, {"name": "1739年出生", "id": 84605}, {"name": "1739年逝世", "id": 92464}, {"name": "1701年逝世", "id": 78751}, {"name": "1701年出生", "id": 84467}, {"name": "1738年出生", "id": 68099}, {"name": "1738年逝世", "id": 92463}, {"name": "1788年出生", "id": 84637}, {"name": "1788年逝世", "id": 92405}, {"name": "1737年逝世", "id": 71989}, {"name": "1737年出生", "id": 84604}, {"name": "1786年出生", "id": 84635}, {"name": "1786年逝世", "id": 92401}, {"name": "1735年出生", "id": 68056}, {"name": "1735年逝世", "id": 68163}, {"name": "1785年出生", "id": 68105}, {"name": "1785年逝世", "id": 92400}, {"name": "1767年出生", "id": 68052}, {"name": "1767年逝世", "id": 92443}, {"name": "1761年出生", "id": 84618}, {"name": "1761年逝世", "id": 92440}, {"name": "1760年出生", "id": 68088}, {"name": "1760年逝世", "id": 92446}, {"name": "1748年出生", "id": 84611}, {"name": "1748年逝世", "id": 92427}, {"name": "1715年逝世", "id": 68257}, {"name": "1715年出生", "id": 68292}, {"name": "1778年逝世", "id": 68287}, {"name": "1778年出生", "id": 84628}, {"name": "1764年逝世", "id": 68320}, {"name": "1764年出生", "id": 84620}, {"name": "1773年出生", "id": 68050}, {"name": "1773年逝世", "id": 92416}, {"name": "1774年出生", "id": 84625}, {"name": "1774年逝世", "id": 92419}, {"name": "1775年出生", "id": 84626}, {"name": "1775年逝世", "id": 92421}, {"name": "1723年出生", "id": 84598}, {"name": "1723年逝世", "id": 92451}, {"name": "1725年逝世", "id": 68266}, {"name": "1725年出生", "id": 84600}, {"name": "1726年出生", "id": 84601}, {"name": "1726年逝世", "id": 92453}, {"name": "1727年逝世", "id": 68261}, {"name": "1727年出生", "id": 84602}, {"name": "1728年出生", "id": 68224}, {"name": "1728年逝世", "id": 92455}, {"name": "1730年逝世", "id": 68293}, {"name": "1730年出生", "id": 70417}, {"name": "1731年出生", "id": 68142}, {"name": "1731年逝世", "id": 92458}, {"name": "1800年出生", "id": 70373}, {"name": "1800年逝世", "id": 92384}, {"name": "1784年出生", "id": 68047}, {"name": "1784年逝世", "id": 92391}, {"name": "1783年逝世", "id": 70418}, {"name": "1783年出生", "id": 84633}, {"name": "1711年出生", "id": 68159}, {"name": "1711年逝世", "id": 92448}, {"name": "1713年出生", "id": 84474}, {"name": "1713年逝世", "id": 92450}, {"name": "1714年出生", "id": 84475}, {"name": "1714年逝世", "id": 92452}, {"name": "1718年逝世", "id": 68254}, {"name": "1718年出生", "id": 84479}, {"name": "1719年逝世", "id": 68265}, {"name": "1719年出生", "id": 84480}, {"name": "1779年逝世", "id": 68305}, {"name": "1779年出生", "id": 84629}, {"name": "美国最高法院案例", "id": 248239}, {"name": "美国最高法院大法官", "id": 459955}, {"name": "美国最高法院模板", "id": 6202680}, {"name": "美國最高法院律政書記", "id": 7411907}, {"name": "1724年建立的行政区划", "id": 3930514}, {"name": "伦敦林奈学会会士", "id": 3779002}, {"name": "1753年描述的分類群", "id": 6697847}, {"name": "1775年描述的分類群", "id": 6702308}, {"name": "1785年發現的天體", "id": 6014718}, {"name": "1788年描述的分類群", "id": 6832368}, {"name": "1789年描述的分類群", "id": 6697836}, {"name": "1760年描述的分類群", "id": 6701026}, {"name": "1799年描述的分類群", "id": 6701030}, {"name": "1798年描述的分類群", "id": 6706113}, {"name": "1763年描述的分类群", "id": 6860572}, {"name": "1754年描述的分类群", "id": 6867930}, {"name": "1794年描述的分類群", "id": 6876047}, {"name": "1790年描述的分類群", "id": 6894028}, {"name": "1791年描述的动物", "id": 6845434}, {"name": "1778年描述的動物", "id": 6002896}, {"name": "七年戰爭戰役", "id": 277896}]}