{"name": "臺灣教育組織", "id": 5636693, "predecessors": [{"name": "教育", "id": 51575}, {"name": "总览", "id": 6349075}], "successors": [{"name": "中華民國教育部", "id": 760990}, {"name": "台灣冠以人名的教育機構", "id": 5175591}, {"name": "台灣學校列表", "id": 608850}, {"name": "台灣女子學校", "id": 1521095}, {"name": "彰化市學校", "id": 7548415}, {"name": "雲林縣小學", "id": 3569933}, {"name": "台灣校園劇", "id": 3760413}, {"name": "臺灣學校背景電影", "id": 6020828}, {"name": "臺中市立國民中學", "id": 465053}, {"name": "臺中市立國民小學", "id": 3368294}, {"name": "臺北市立國民中學", "id": 138166}, {"name": "臺北市立國民小學", "id": 339012}, {"name": "新北市立國民中學", "id": 1488344}, {"name": "新北市立國民小學", "id": 3757957}, {"name": "新北市立普通型高級中等學校", "id": 3062655}, {"name": "台灣大專院校系統與聯盟", "id": 4231159}, {"name": "北區技職校院區域教學資源中心", "id": 4402667}, {"name": "南區技職校院區域教學資源中心", "id": 4402925}, {"name": "中華民國大專院校的附設學校", "id": 6843669}, {"name": "國立臺灣大學文學院校友", "id": 5986493}, {"name": "國立臺灣大學社會科學院校友", "id": 5986568}, {"name": "國立臺灣大學法律學院校友", "id": 5986555}, {"name": "台灣高級中等學校模板", "id": 4231178}]}