{"name": "唐朝官制", "id": 575533, "predecessors": [{"name": "中国历史", "id": 33589}, {"name": "文化", "id": 42322}], "successors": [{"name": "唐朝官员", "id": 2759797}, {"name": "唐朝武官", "id": 2986972}, {"name": "唐朝刺史", "id": 3333315}, {"name": "唐朝太守", "id": 4047029}, {"name": "唐朝别驾", "id": 4052116}, {"name": "唐朝司马", "id": 4052181}, {"name": "唐朝县令", "id": 4090719}, {"name": "唐朝县丞", "id": 4090720}, {"name": "唐朝县尉", "id": 4090732}, {"name": "唐朝长史", "id": 4090847}, {"name": "唐朝参军", "id": 4102408}, {"name": "唐朝观察使", "id": 5913947}, {"name": "唐朝大都护", "id": 4120761}, {"name": "安西都护", "id": 8107411}]}