{"name": "和平", "id": 58101, "predecessors": [{"name": "国际安全", "id": 1073315}, {"name": "倫理學", "id": 57308}, {"name": "原則", "id": 1244774}, {"name": "暴力", "id": 1244701}], "successors": [{"name": "和约", "id": 81532}, {"name": "反戰運動", "id": 589703}, {"name": "裁軍", "id": 959000}, {"name": "冷战条约", "id": 1412815}, {"name": "战争法", "id": 1662353}, {"name": "第二次世界大战战后影响", "id": 1412801}, {"name": "转型正义", "id": 6353371}, {"name": "人類發展指數", "id": 4802966}, {"name": "中華民國國軍退除役官兵輔導委員會", "id": 3703286}, {"name": "朝韩非军事区", "id": 1365605}, {"name": "贫困", "id": 1535067}, {"name": "女性億萬富豪", "id": 1233484}, {"name": "前億萬富豪", "id": 6367678}]}