{"name": "出版業", "id": 59761, "predecessors": [{"name": "大眾媒體", "id": 58343}, {"name": "文化", "id": 42322}], "successors": [{"name": "版权", "id": 33058}, {"name": "印刷", "id": 72452}, {"name": "工具书", "id": 65026}, {"name": "教科书", "id": 80943}, {"name": "標點符號", "id": 79158}, {"name": "语法", "id": 117922}, {"name": "广播", "id": 65119}, {"name": "图书封面", "id": 81262}, {"name": "书籍模板", "id": 225892}, {"name": "書籍列表", "id": 390104}, {"name": "書籍類型", "id": 650232}, {"name": "閱讀", "id": 790212}, {"name": "德语报纸", "id": 3521109}, {"name": "处女作小说", "id": 3674447}, {"name": "13世紀書籍", "id": 1164385}, {"name": "11世紀書籍", "id": 4996462}, {"name": "7世紀書籍", "id": 5096835}, {"name": "前6世紀書籍", "id": 6230889}, {"name": "手抄本", "id": 1165229}, {"name": "文字冒險遊戲", "id": 417424}, {"name": "週報", "id": 3917261}, {"name": "丛书", "id": 696569}, {"name": "電子遊戲發行商", "id": 1812036}, {"name": "朝日新聞社人物", "id": 5034787}, {"name": "讀賣新聞集團人物", "id": 5949654}, {"name": "紐約時報人物", "id": 4738897}, {"name": "美国杂志编辑", "id": 5629570}, {"name": "纽约客人物", "id": 6770951}, {"name": "學術出版", "id": 1431450}, {"name": "美國書籍", "id": 1214523}, {"name": "美国诗人", "id": 41453}, {"name": "中华人民共和国日报", "id": 4678080}, {"name": "散佚書籍", "id": 855622}, {"name": "短篇小說集", "id": 1115532}, {"name": "日記", "id": 1291530}, {"name": "烹飪作家", "id": 7973163}, {"name": "改编成电影的中华人民共和国小说", "id": 3999816}, {"name": "改编成电视剧的中华人民共和国小说", "id": 6650583}, {"name": "改編成電影的台灣小說", "id": 3999870}, {"name": "美国杂志", "id": 59398}, {"name": "星際大戰", "id": 125102}, {"name": "黑马漫画出版物", "id": 7140450}, {"name": "辛普森一家", "id": 669332}, {"name": "漫畫出版社", "id": 798685}, {"name": "電子書", "id": 1199596}]}