{"name": "政治地理学", "id": 610624, "predecessors": [{"name": "人文地理學", "id": 732091}, {"name": "政治學", "id": 70127}], "successors": [{"name": "殖民主义", "id": 136230}, {"name": "分治地區", "id": 460316}, {"name": "區域研究", "id": 258982}, {"name": "民族主义研究学者", "id": 7545335}, {"name": "領土變更相關條約", "id": 588455}, {"name": "兼并扩张", "id": 5067548}, {"name": "中华人民共和国领土变化", "id": 6949176}, {"name": "领土收复主义", "id": 265954}, {"name": "主權運動", "id": 410462}, {"name": "國族認同矛盾", "id": 5391025}, {"name": "中華人民共和國爭議地區", "id": 1873754}, {"name": "非洲前殖民地", "id": 7633168}, {"name": "美洲前英国殖民地或受保护国", "id": 5463401}, {"name": "微型國家", "id": 167430}, {"name": "城邦", "id": 1253554}, {"name": "未被普遍承认的历史国家", "id": 2908606}, {"name": "傀儡政权", "id": 440262}, {"name": "法属波利尼西亚无人岛", "id": 5202880}, {"name": "美屬薩摩亞聚居地", "id": 6955406}, {"name": "夏威夷州普查规定居民点", "id": 5178677}, {"name": "夏威夷州非建制地區", "id": 6150671}, {"name": "夏威夷縣普查規定居民點", "id": 6831633}, {"name": "属地首府", "id": 4419545}, {"name": "香港人", "id": 39760}, {"name": "澳門人", "id": 78443}, {"name": "波多黎各棒球運動員", "id": 657494}]}