{"name": "台灣民間信仰", "id": 623975, "predecessors": [{"name": "東亞民間信仰", "id": 1269016}, {"name": "台灣文化", "id": 56568}, {"name": "人文地理學", "id": 732091}], "successors": [{"name": "台灣民俗陣頭", "id": 603299}, {"name": "王爺信仰", "id": 1472236}, {"name": "台灣媽祖信仰", "id": 2792726}, {"name": "台灣漢族民間信仰", "id": 3799773}, {"name": "臺灣人物神", "id": 6366300}, {"name": "台灣義民廟", "id": 6733884}, {"name": "台灣陰廟", "id": 6837925}, {"name": "澎湖縣鸞堂", "id": 6102752}, {"name": "台灣城隍廟", "id": 1669657}, {"name": "台灣關帝廟", "id": 1719641}, {"name": "台灣王爺廟", "id": 3334574}, {"name": "台灣玄天上帝廟", "id": 5393589}, {"name": "台灣三十三觀音靈場", "id": 4746271}, {"name": "台北市觀音寺", "id": 7005926}]}