{"name": "視覺藝術", "id": 66057, "predecessors": [{"name": "視覺", "id": 455335}, {"name": "社会科学", "id": 41504}], "successors": [{"name": "设计", "id": 47059}, {"name": "摄影", "id": 47073}, {"name": "數位藝術", "id": 4805362}, {"name": "日本美術館", "id": 354944}, {"name": "台灣的美術館", "id": 354970}, {"name": "美國美術館", "id": 354972}, {"name": "日本庭園", "id": 442960}, {"name": "意大利画家", "id": 86979}, {"name": "上海市的美术馆", "id": 3761805}, {"name": "中国漫画作品", "id": 1551935}, {"name": "丁丁历险记书籍", "id": 5661423}, {"name": "宗教题材电影", "id": 1811080}, {"name": "種族題材電影", "id": 1460587}, {"name": "兒童題材電影", "id": 6021115}, {"name": "变身题材电影", "id": 7209542}, {"name": "失踪人口题材电影", "id": 7394255}, {"name": "圣母玛利亚相关绘画作品", "id": 1279896}, {"name": "藝術作品中的鳥", "id": 4554043}, {"name": "賽車電影", "id": 1406185}, {"name": "黑幫電影", "id": 560580}, {"name": "連環殺手題材電影", "id": 1356921}, {"name": "監獄電影", "id": 1398745}, {"name": "槍戰片", "id": 1781847}, {"name": "恐怖活動電影", "id": 2773415}, {"name": "海盗电影", "id": 2834269}, {"name": "霸凌題材電影", "id": 2856449}, {"name": "推理电影", "id": 2956877}, {"name": "報復題材電影", "id": 3379267}, {"name": "法律题材电影", "id": 3818210}, {"name": "貪污相關電影", "id": 6412031}, {"name": "IRIS系列", "id": 3620559}, {"name": "美國間諜片", "id": 1342843}, {"name": "兒童電影", "id": 953552}, {"name": "LGBT相關電影", "id": 1221739}, {"name": "孤兒題材電影", "id": 1430877}, {"name": "雙胞胎題材電影", "id": 3102514}, {"name": "移民题材电影", "id": 3894773}, {"name": "擬人化角色電影", "id": 3894904}, {"name": "老人题材电影", "id": 3905163}, {"name": "皇室成員相關電影", "id": 3944889}, {"name": "黃飛鴻電影", "id": 2962884}, {"name": "忍者片", "id": 2764938}, {"name": "偵探主角題材電影", "id": 2979953}, {"name": "警察主角題材電影", "id": 2998533}, {"name": "殺手主角題材電影", "id": 3355375}, {"name": "教師主角電影", "id": 3757603}, {"name": "演员主角题材电影", "id": 6955079}, {"name": "女性主義電影", "id": 1449261}, {"name": "女孩和枪电影", "id": 3179690}, {"name": "女性題材電影", "id": 4025197}, {"name": "環境保護電影", "id": 714489}, {"name": "冷戰電影", "id": 1355683}, {"name": "反烏托邦電影", "id": 1360492}, {"name": "美國政治劇情片", "id": 1355754}, {"name": "美國政治驚悚片", "id": 1356341}, {"name": "白宫背景电影", "id": 7872725}, {"name": "勵志題材影片", "id": 1798676}, {"name": "教育家題材電影", "id": 3700616}, {"name": "精神病題材電影", "id": 1356478}, {"name": "失憶症題材電影", "id": 3121459}, {"name": "家庭題材電影", "id": 1802371}, {"name": "飲食題材電影", "id": 3103276}, {"name": "死亡題材電影", "id": 3700500}, {"name": "學校背景電影", "id": 2856496}, {"name": "美國青春電影", "id": 1826963}, {"name": "中国青春电影", "id": 3466314}, {"name": "日本青春電影", "id": 3616547}, {"name": "臺灣青春電影", "id": 6021140}, {"name": "藥物題材電影", "id": 6834381}, {"name": "烹飪電影", "id": 1434910}, {"name": "足球電影", "id": 643028}, {"name": "功夫片", "id": 767503}, {"name": "拳擊電影", "id": 1392517}, {"name": "賭博片", "id": 512155}, {"name": "音樂及音樂家題材電影", "id": 1454690}, {"name": "電影題材電影", "id": 3402392}, {"name": "死亡題材畫作", "id": 5976356}, {"name": "政治宣傳海報", "id": 3398622}, {"name": "火神", "id": 894874}, {"name": "美國海軍陸戰隊題材電影", "id": 7098086}, {"name": "美國陸軍題材電影", "id": 7098101}, {"name": "2010年代間諜喜劇片", "id": 7784783}, {"name": "各類型攝影", "id": 1420037}]}