{"name": "基督教教會與教派", "id": 66169, "predecessors": [{"name": "基督教", "id": 33583}, {"name": "思想", "id": 288377}, {"name": "分类系统", "id": 1575681}], "successors": [{"name": "基督教新教教派", "id": 1482974}, {"name": "被天主教会处以绝罚者", "id": 6553475}, {"name": "英格蘭教會教區", "id": 3061871}, {"name": "東正教", "id": 182655}, {"name": "東儀天主教會", "id": 1019918}, {"name": "東正教聖人", "id": 1255142}, {"name": "聖公宗聖人", "id": 1544031}, {"name": "天主教圣人", "id": 1570815}, {"name": "天主教君主", "id": 1129438}, {"name": "天主教皈依者", "id": 1766711}, {"name": "脫離天主教者", "id": 4648903}, {"name": "俄罗斯正教会主教座堂", "id": 2887546}, {"name": "天主教神学家", "id": 2887499}, {"name": "由天主教改信信义宗者", "id": 7055741}, {"name": "美國福音主義者", "id": 5413276}, {"name": "法国天主教主教座堂", "id": 1014866}, {"name": "德国天主教主教座堂", "id": 1014885}, {"name": "波蘭天主教主教座堂", "id": 4490108}, {"name": "意大利天主教主教座堂", "id": 4652442}, {"name": "西班牙天主教主教座堂", "id": 4652447}, {"name": "中国天主教主教座堂", "id": 1011902}, {"name": "越南天主教主教座堂", "id": 1029676}, {"name": "美國天主教主教座堂", "id": 3384769}, {"name": "埃斯特家族", "id": 6325398}, {"name": "阿道夫·希特勒", "id": 1806643}, {"name": "天主教政黨", "id": 1774506}, {"name": "天主教历史", "id": 1023283}, {"name": "德国天主教教区", "id": 559859}, {"name": "法国天主教教区", "id": 910041}, {"name": "烏克蘭天主教教區", "id": 2782684}, {"name": "19世纪美国圣公会教徒", "id": 7249145}, {"name": "20世纪美国圣公会徒", "id": 7686063}, {"name": "天主教澳门教区主教", "id": 1489270}, {"name": "耶和华见证人", "id": 410626}, {"name": "摩爾門教", "id": 4534325}, {"name": "英格蘭天主教徒", "id": 2895159}]}