{"name": "17世纪出生", "id": 68151, "predecessors": [{"name": "曆法", "id": 45146}, {"name": "年代学", "id": 454712}], "successors": [{"name": "1611年出生", "id": 68212}, {"name": "1610年出生", "id": 84400}, {"name": "1615年出生", "id": 84402}, {"name": "1616年出生", "id": 84403}, {"name": "1617年出生", "id": 84404}, {"name": "1618年出生", "id": 84405}, {"name": "1619年出生", "id": 84406}, {"name": "1678年出生", "id": 68162}, {"name": "1670年出生", "id": 84444}, {"name": "1671年出生", "id": 84445}, {"name": "1675年出生", "id": 84447}, {"name": "1676年出生", "id": 84448}, {"name": "1677年出生", "id": 84449}, {"name": "1679年出生", "id": 84450}, {"name": "1654年出生", "id": 68166}, {"name": "1653年出生", "id": 68175}, {"name": "1651年出生", "id": 84428}, {"name": "1652年出生", "id": 84429}, {"name": "1655年出生", "id": 84430}, {"name": "1656年出生", "id": 84431}, {"name": "1657年出生", "id": 84432}, {"name": "1659年出生", "id": 84434}, {"name": "1633年出生", "id": 80994}, {"name": "1630年出生", "id": 84412}, {"name": "1631年出生", "id": 84413}, {"name": "1632年出生", "id": 84414}, {"name": "1634年出生", "id": 84415}, {"name": "1635年出生", "id": 84416}, {"name": "1639年出生", "id": 84419}, {"name": "1621年出生", "id": 68198}, {"name": "1622年出生", "id": 68203}, {"name": "1629年出生", "id": 68227}, {"name": "1628年出生", "id": 78752}, {"name": "1620年出生", "id": 84407}, {"name": "1623年出生", "id": 84408}, {"name": "1627年出生", "id": 84411}, {"name": "1605年出生", "id": 68223}, {"name": "1606年出生", "id": 68242}, {"name": "1608年出生", "id": 68250}, {"name": "1607年出生", "id": 71994}, {"name": "1604年出生", "id": 71995}, {"name": "1603年出生", "id": 71996}, {"name": "1609年出生", "id": 84399}, {"name": "1642年出生", "id": 68260}, {"name": "1645年出生", "id": 68283}, {"name": "1640年出生", "id": 84420}, {"name": "1641年出生", "id": 84421}, {"name": "1643年出生", "id": 84422}, {"name": "1644年出生", "id": 84423}, {"name": "1646年出生", "id": 84424}, {"name": "1647年出生", "id": 84425}, {"name": "1663年出生", "id": 84436}, {"name": "1664年出生", "id": 84437}, {"name": "1665年出生", "id": 84439}, {"name": "1666年出生", "id": 84440}, {"name": "1667年出生", "id": 84441}, {"name": "1668年出生", "id": 84442}, {"name": "1669年出生", "id": 84443}, {"name": "1681年出生", "id": 68271}, {"name": "1689年出生", "id": 79336}, {"name": "1680年出生", "id": 84451}, {"name": "1682年出生", "id": 84452}, {"name": "1683年出生", "id": 84453}, {"name": "1688年出生", "id": 84456}, {"name": "1693年出生", "id": 68279}, {"name": "1694年出生", "id": 79306}, {"name": "1690年出生", "id": 84457}, {"name": "1691年出生", "id": 84458}, {"name": "1695年出生", "id": 84460}, {"name": "1699年出生", "id": 84465}]}