{"name": "中国大陆电视节目", "id": 698048, "predecessors": [{"name": "文化", "id": 42322}, {"name": "中国文化", "id": 33600}], "successors": [{"name": "中國大陸綜藝節目", "id": 3044383}, {"name": "江苏卫视电视节目", "id": 1740016}, {"name": "东方卫视节目", "id": 1908873}, {"name": "浙江卫视电视节目", "id": 3445214}, {"name": "北京卫视节目", "id": 6523246}, {"name": "安徽卫视电视剧", "id": 3795479}, {"name": "芒果TV自制综艺节目", "id": 5758814}, {"name": "优酷土豆自制节目", "id": 6517706}, {"name": "腾讯视频自制节目", "id": 6368327}, {"name": "企鹅影视出品综艺节目", "id": 6411550}, {"name": "中国大陆电视剧列表", "id": 3532833}, {"name": "愛爾達電視外購陸劇", "id": 8377084}, {"name": "中天電視外購陸劇", "id": 8675045}, {"name": "八大電視外購陸劇", "id": 8716540}, {"name": "緯來電視外購陸劇", "id": 8716541}]}