{"name": "人文地理學", "id": 732091, "predecessors": [{"name": "人类学", "id": 36195}, {"name": "地理学分支", "id": 5694865}, {"name": "社会科学", "id": 41504}], "successors": [{"name": "人口", "id": 67007}, {"name": "政治地理学", "id": 610624}, {"name": "文化地理學", "id": 1049162}, {"name": "土地管理", "id": 1164456}, {"name": "地母神", "id": 1740113}, {"name": "拉姆薩公約登錄地", "id": 2994622}, {"name": "IUCN分类II", "id": 1132376}, {"name": "海洋國家公園", "id": 1688890}, {"name": "国家公园模板", "id": 3639459}, {"name": "国家公园列表", "id": 5364747}, {"name": "IUCN分类V", "id": 1132379}, {"name": "IUCN分类IV", "id": 1396546}, {"name": "IUCN分类Ia", "id": 1575367}, {"name": "IUCN分类III", "id": 1575368}, {"name": "IUCN分类VI", "id": 1575370}, {"name": "清朝庙宇", "id": 4322963}, {"name": "中国关帝庙", "id": 4954822}, {"name": "中国玉皇上帝庙", "id": 6601205}, {"name": "台灣清治時期廟宇", "id": 7393826}, {"name": "中国新兴宗教", "id": 1473717}, {"name": "耶和华见证人", "id": 410626}, {"name": "山達基信徒", "id": 4756657}, {"name": "坦桑尼亞天主教教區", "id": 3357156}, {"name": "中国道教协会副会长", "id": 5700529}, {"name": "山西孔庙", "id": 2812758}, {"name": "浙江孔庙", "id": 3467141}, {"name": "四川文廟", "id": 4973369}, {"name": "藏傳佛教", "id": 72221}, {"name": "日本佛教", "id": 686136}, {"name": "泰國佛教徒", "id": 2896071}, {"name": "馬來西亞佛教徒", "id": 2892811}, {"name": "越南佛教徒", "id": 2896079}, {"name": "巴黎教堂", "id": 968055}, {"name": "维也纳教堂", "id": 968083}, {"name": "美國猶太人", "id": 533719}, {"name": "中国土地制度", "id": 680530}, {"name": "土地改革", "id": 6746324}, {"name": "烏克蘭猶太人", "id": 493507}, {"name": "立陶宛犹太人", "id": 611077}, {"name": "匈牙利犹太人", "id": 1079113}, {"name": "阿什肯納茲猶太人", "id": 5499444}, {"name": "納粹大屠殺", "id": 1023791}, {"name": "波蘭猶太人", "id": 1078617}, {"name": "波兰犹太人历史", "id": 7108634}, {"name": "南非天主教教區", "id": 3067347}, {"name": "尼日利亞天主教教區", "id": 3248066}, {"name": "台灣道教", "id": 413567}, {"name": "台灣民間信仰", "id": 623975}, {"name": "日本神话", "id": 166383}, {"name": "修验道", "id": 634206}, {"name": "日本民間信仰", "id": 1269015}, {"name": "城隍", "id": 2768666}, {"name": "韓國天主教徒", "id": 2920684}, {"name": "印度錫克教徒", "id": 1307662}, {"name": "印度穆斯林", "id": 1489295}, {"name": "印度印度教徒", "id": 2890007}, {"name": "印度佛教徒", "id": 2895710}, {"name": "韓國佛教徒", "id": 2896022}, {"name": "韓國新教徒", "id": 2889105}, {"name": "印度尼西亞穆斯林", "id": 1238499}, {"name": "古希腊宗教", "id": 2816576}, {"name": "秘魯天主教教區", "id": 1856218}, {"name": "委內瑞拉天主教教區", "id": 3365559}, {"name": "法國穆斯林", "id": 1279272}, {"name": "罗马教堂", "id": 925153}, {"name": "伊斯坦堡清真寺", "id": 1295198}, {"name": "印度尼西亚天主教教区", "id": 909032}, {"name": "朝鮮半島佛教出家眾", "id": 2906849}, {"name": "猶太裔美國人", "id": 3720485}, {"name": "加拿大猶太人", "id": 1079846}, {"name": "立陶宛犹太裔美国人", "id": 6979544}, {"name": "德国犹太裔美国人", "id": 6979558}, {"name": "俄罗斯犹太裔美国人", "id": 6979560}, {"name": "波兰犹太裔美国人", "id": 6979574}, {"name": "匈牙利犹太裔美国人", "id": 6979749}, {"name": "乌克兰犹太裔美国人", "id": 6979882}, {"name": "白俄罗斯犹太裔美国人", "id": 6979884}, {"name": "奥地利犹太裔美国人", "id": 6981801}, {"name": "罗马尼亚犹太裔美国人", "id": 6983023}, {"name": "日本佛寺", "id": 162233}, {"name": "已不存在国家的首都", "id": 7393343}, {"name": "保密行政區", "id": 785916}, {"name": "拜占庭帝国军区", "id": 6463668}, {"name": "波森省人", "id": 6657938}, {"name": "伦敦教堂", "id": 968064}, {"name": "古都", "id": 1757835}, {"name": "台灣佛教徒", "id": 1684044}, {"name": "台灣穆斯林", "id": 1684335}, {"name": "臺灣基督徒", "id": 4646241}, {"name": "台灣道教徒", "id": 8186452}, {"name": "国家", "id": 33603}, {"name": "克羅地亞教堂", "id": 4134809}, {"name": "俄羅斯國家公園", "id": 1617840}, {"name": "芬蘭國家公園", "id": 5245279}, {"name": "土耳其國家公園", "id": 7409432}, {"name": "法國猶太人", "id": 1078613}, {"name": "德國猶太人", "id": 641664}, {"name": "犹太裔德国人", "id": 6980540}, {"name": "德国反犹太主义", "id": 7028462}, {"name": "義大利猶太人", "id": 1078986}, {"name": "捷克猶太人", "id": 1078620}]}