{"name": "宗教哲學", "id": 73383, "predecessors": [{"name": "宗教学", "id": 79228}, {"name": "人類行為", "id": 665955}, {"name": "維基百科管理", "id": 501839}], "successors": [{"name": "神學", "id": 73378}, {"name": "无神论", "id": 332904}, {"name": "宗教哲学家", "id": 3904058}, {"name": "超自然恐怖片", "id": 1342233}, {"name": "宗教迫害", "id": 1574968}, {"name": "古希腊宗教", "id": 2816576}, {"name": "死後世界", "id": 1631234}, {"name": "創造神", "id": 2910153}, {"name": "天部", "id": 3471823}, {"name": "惡魔", "id": 141610}, {"name": "巫术", "id": 176537}, {"name": "鬼", "id": 923430}, {"name": "不死生物", "id": 1356896}, {"name": "大成就者", "id": 1364618}, {"name": "基督教新教神秘主义者", "id": 8416197}, {"name": "被天主教会处以绝罚者", "id": 6553475}]}