{"name": "蜘蛛目", "id": 73979, "predecessors": [{"name": "动物行为学", "id": 486569}], "successors": [{"name": "蟹蛛科", "id": 791051}, {"name": "跳蛛科", "id": 1149124}, {"name": "圓蛛科", "id": 3665870}, {"name": "隙蛛属", "id": 1149092}, {"name": "豹蛛属", "id": 1149096}, {"name": "舞蛛属", "id": 1149111}, {"name": "狼蛛属", "id": 1149113}, {"name": "管巢蛛属", "id": 1149104}, {"name": "红螯蛛属", "id": 1149125}, {"name": "肖峭属", "id": 1149108}, {"name": "猫蛛属", "id": 1149115}, {"name": "蜘蛛侠", "id": 1275880}, {"name": "球蛛属", "id": 1149098}, {"name": "希蛛属", "id": 1149114}, {"name": "圆腹蛛属", "id": 1149119}, {"name": "斑皿蛛属", "id": 1149117}, {"name": "盖蛛属", "id": 1149120}, {"name": "平腹蛛属", "id": 1149106}, {"name": "狂蛛属", "id": 1149121}]}