{"name": "技術史", "id": 790479, "predecessors": [{"name": "經濟史", "id": 115078}, {"name": "技術史", "id": 790479}, {"name": "虛構", "id": 69954}], "successors": [{"name": "建筑史", "id": 98699}, {"name": "计算机历史", "id": 450836}, {"name": "醫學史", "id": 680991}, {"name": "铁路废线", "id": 756649}, {"name": "日本城堡", "id": 414894}, {"name": "日本鐵道史", "id": 3523547}, {"name": "土木學會選獎土木遺產", "id": 6940110}, {"name": "土木學會田中獎", "id": 7226516}, {"name": "天文仪器", "id": 180815}, {"name": "2017年面世的手機", "id": 5898917}, {"name": "2016年面世的手機", "id": 5898934}, {"name": "2015年面世的手機", "id": 5904060}, {"name": "2014年面世的手機", "id": 5917813}, {"name": "2013年面世的手機", "id": 5988742}, {"name": "2018年面世的手機", "id": 6012391}, {"name": "2019年面世的手機", "id": 6431614}, {"name": "2020年面世的手機", "id": 6910117}, {"name": "2021年面世的手機", "id": 7356445}, {"name": "2022年面世的手機", "id": 7866950}, {"name": "蘇聯科技", "id": 1561724}, {"name": "20世紀工程師", "id": 7085069}, {"name": "1990年代汽車", "id": 5395500}, {"name": "2010年代汽車", "id": 5395499}, {"name": "2010年代公路片", "id": 7613401}, {"name": "2013年航空事故", "id": 3533109}, {"name": "2015年航空事故", "id": 4500113}, {"name": "2015年软件", "id": 3906235}, {"name": "工业革命", "id": 549197}, {"name": "古代天文学", "id": 1704276}, {"name": "埃及发明", "id": 8576758}, {"name": "农业史", "id": 76527}, {"name": "技術史", "id": 790479}, {"name": "歷史性工程地標", "id": 1246016}, {"name": "汽车先驱", "id": 5602093}, {"name": "2010年面世的汽車", "id": 5743986}, {"name": "無線電", "id": 66088}, {"name": "无线通信", "id": 159014}, {"name": "偏振", "id": 1609799}, {"name": "日本已结业铁路公司", "id": 750627}, {"name": "中国已结业铁路公司", "id": 6982830}, {"name": "曼哈顿计划历史", "id": 7264068}, {"name": "中国核工业人物", "id": 6824292}, {"name": "已結業電子遊戲公司", "id": 889933}]}