{"name": "嵌入式系统", "id": 97396, "predecessors": [{"name": "電子學", "id": 73177}, {"name": "计算机科学", "id": 326427}, {"name": "分类系统", "id": 1575681}], "successors": [{"name": "微控制器", "id": 377614}, {"name": "嵌入式操作系统", "id": 519419}, {"name": "无人机", "id": 527586}, {"name": "机器人学", "id": 557188}, {"name": "掌上遊戲機", "id": 796781}, {"name": "航空电子学", "id": 1553617}, {"name": "单片系统", "id": 4712166}, {"name": "BIOS", "id": 379236}, {"name": "售後韌體", "id": 1170544}, {"name": "实时操作系统", "id": 495859}, {"name": "智能卡", "id": 145760}, {"name": "智能手機", "id": 251233}, {"name": "智能手表", "id": 3888178}]}